{
    "Ar36": {
        "error": 0.042053530631223884, 
        "fit": "Parabolic", 
        "value": 1.3434167108302475
    }, 
    "Ar37": {
        "error": 0.019678259787226114, 
        "fit": "linear", 
        "value": 19.52343645539813
    }, 
    "Ar38": {
        "error": 0.022343218270781732, 
        "fit": "linear", 
        "value": 1.9556386395419658
    }, 
    "Ar39": {
        "error": 0.03745551301030589, 
        "fit": "Parabolic", 
        "value": 8.592023093766823
    }, 
    "Ar40": {
        "error": 0.32978804741351114, 
        "fit": "Parabolic", 
        "value": 3267.6835502265294
    }
}