{
    "Ar36": {
        "error": 0.04141748437206358, 
        "fit": "Parabolic", 
        "value": 3.3659979758902114
    }, 
    "Ar37": {
        "error": 0.0192667330043766, 
        "fit": "linear", 
        "value": 32.19183366275373
    }, 
    "Ar38": {
        "error": 0.02290359521933483, 
        "fit": "linear", 
        "value": 4.15127746281648
    }, 
    "Ar39": {
        "error": 0.039145964640316, 
        "fit": "Parabolic", 
        "value": 22.182647022280968
    }, 
    "Ar40": {
        "error": 0.9663714486815854, 
        "fit": "Parabolic", 
        "value": 8499.245655907254
    }
}