{
    "AX": {
        "error": 0.02971753852784111, 
        "fit": "average", 
        "value": -0.12355986387825882
    }, 
    "H1": {
        "error": 0.017207270800164362, 
        "fit": "average", 
        "value": 0.07177827636195015
    }, 
    "H2": {
        "error": 0.012854406578038245, 
        "fit": "average", 
        "value": -0.11394738667645701
    }, 
    "L1": {
        "error": 0.016640198688496973, 
        "fit": "average", 
        "value": -0.040853243231920223
    }, 
    "L2(CDD)": {
        "error": 8.691620769885139e-06, 
        "fit": "average", 
        "value": 3.683086145322733e-05
    }
}